vlsift/__init__.py
vlsift/utils.py
vlsift/sift/__init__.py
vlsift/sift/sift.py
vlsift/sift/cysift.cpython-313-x86_64-linux-gnu.so
vlsift/sift/tests/__init__.py
vlsift/sift/tests/sift_test.py
vlsift/data/ascent.frame
vlsift/data/ascent.descr
vlsift/_vl/__init__.py
vlsift-0.1.2.dist-info/WHEEL
vlsift-0.1.2.dist-info/METADATA
vlsift-0.1.2.dist-info/top_level.txt
vlsift-0.1.2.dist-info/RECORD
vlsift-0.1.2.dist-info/LICENSE.txt
