Metadata-Version: 2.2
Name: vlsift
Version: 0.1.2
Summary: Cython wrapper of the VLFeat toolkit
Home-page: https://cars.readthedocs.io/
Author: CNES
Author-email: cars@cnes.fr
License: ibug
Project-URL: Source, https://github.com/CNES/cars
Project-URL: Documentation, https://cars.readthedocs.io/en/latest/
Keywords: vlsift,sift,vlfeat,cars
Platform: any
Classifier: Development Status :: 4 - Beta
Classifier: Intended Audience :: Developers
Classifier: Intended Audience :: End Users/Desktop
Classifier: Intended Audience :: Science/Research
Classifier: Environment :: Console
Classifier: Topic :: Software Development :: Libraries :: Python Modules
Classifier: Programming Language :: Python
Classifier: Programming Language :: Python :: 3.9
License-File: LICENSE.txt
Dynamic: summary
